LICENSE
README.md
setup.py
fastplot/__init__.py
fastplot.egg-info/PKG-INFO
fastplot.egg-info/SOURCES.txt
fastplot.egg-info/dependency_links.txt
fastplot.egg-info/requires.txt
fastplot.egg-info/top_level.txt