Metadata-Version: 2.1
Name: fastplot
Version: 1.5.0
Summary: Are you bored of re-writing code for each plot? Create publication-quality plots with a simple interface over matplotlib.
Home-page: https://github.com/marty90/fastplot
Download-URL: https://github.com/marty90/fastplot/tarball/1.5.0
Author: Martino Trevisan
Author-email: martino.trevisan@polito.it
Maintainer: Martino Trevisan
Maintainer-email: martino.trevisan@polito.it
License: GNU GENERAL PUBLIC LICENSE v3
License-File: LICENSE
